[
  {
    "name": "pnp-list-formatting-number-data-bar-multi-color",
    "reponame": "number-data-bar-multi-color",
    "source": "pnp",
    "title": "Multi-Colored Databars",
    "shortDescription": "Ta próbka formatowania kolumn demonstrates how to show the number column as data bars with multiple colors.",
    "url": "https://github.com/pnp/list-formatting/tree/master/column-samples/number-data-bar-multi-color",
    "longDescription": [
      "Ta próbka formatowania kolumn demonstrates how to show the number column as data bars with multiple colors."
    ],
    "creationDateTime": "2017-11-02T00:00:00.000Z",
    "updateDateTime": "2019-05-17T00:00:00.000Z",
    "products": [
      "SharePoint",
      "Microsoft Lists"
    ],
    "metadata": [
      {
        "key": "LIST-SAMPLE-TYPE",
        "value": "Column"
      },
      {
        "key": "SHAREPOINT-COMPATIBILITY",
        "value": "SharePoint 2019, SharePoint Online"
      },
      {
        "key": "SAMPLE-CATEGORIES",
        "value": ""
      },
      {
        "key": "LIST-COLUMN-TYPE",
        "value": "Number"
      },
      {
        "key": "FORMATTING-TOKENS",
        "value": ""
      },
      {
        "key": "FORMATTING-OPERATORS",
        "value": ""
      },
      {
        "key": "FORMATTING-ACTIONS",
        "value": ""
      },
      {
        "key": "FORMATTING-FEATURES",
        "value": ""
      },
      {
        "key": "CLASSES",
        "value": ""
      }
    ],
    "thumbnails": [
      {
        "type": "image",
        "order": 100,
        "url": "https://raw.githubusercontent.com/pnp/List-Formatting/master/column-samples/number-data-bar-multi-color/assets/screenshot.png",
        "alt": "zrzut ekranu"
      }
    ],
    "authors": [
      {
        "gitHubAccount": "ganesh-sanap",
        "pictureUrl": "https://github.com/ganesh-sanap.png",
        "name": "Ganesh Sanap"
      }
    ],
    "references": [
      {
        "name": "Użyj formatowania kolumn do dostosowania SharePoint",
        "description": "Możesz użyć formatowania kolumn, aby dostosować sposób wyświetlania pól na listach i w bibliotekach SharePoint. W tym celu tworzysz obiekt JSON opisujący elementy wyświetlane wtedy, gdy pole jest uwzględnione w widoku listy, oraz style stosowane do tych elementów. Formatowanie kolumn nie zmienia danych elementu listy ani pliku; zmienia jedynie sposób ich wyświetlania użytkownikom przeglądającym listę.",
        "url": "https://docs.microsoft.com/sharepoint/dev/declarative-customization/column-formatting"
      }
    ]
  }
]
