[
  {
    "name": "pnp-list-formatting-hyperlink-click-count",
    "reponame": "hyperlink-click-count",
    "source": "pnp",
    "title": "Count the Number of Clicks on a Link",
    "shortDescription": "Ta próbka pokazuje counting the number of clicks on a link.",
    "url": "https://github.com/pnp/List-Formatting/tree/master/column-samples/hyperlink-click-count",
    "longDescription": [
      "Ta próbka pokazuje counting the number of clicks on a link. By keeping track of the number of link clicks, you can figure out which links are popular with users."
    ],
    "creationDateTime": "2021-12-11T00:00:00.000Z",
    "updateDateTime": "2021-12-11T00:00:00.000Z",
    "products": [
      "SharePoint",
      "Microsoft Lists"
    ],
    "metadata": [
      {
        "key": "LIST-SAMPLE-TYPE",
        "value": "Column"
      },
      {
        "key": "SHAREPOINT-COMPATIBILITY",
        "value": "SharePoint Online"
      },
      {
        "key": "SAMPLE-CATEGORIES",
        "value": "Inline Editing"
      },
      {
        "key": "LIST-COLUMN-TYPE",
        "value": "Hyperlink"
      },
      {
        "key": "FORMATTING-TOKENS",
        "value": ""
      },
      {
        "key": "FORMATTING-OPERATORS",
        "value": ""
      },
      {
        "key": "FORMATTING-ACTIONS",
        "value": "setValue"
      },
      {
        "key": "FORMATTING-FEATURES",
        "value": ""
      },
      {
        "key": "CLASSES",
        "value": "ms-fontColor-themePrimary, ms-bgColor-themePrimary, ms-bgColor-themePrimary--hover, ms-bgColor-themeLight, ms-bgColor-themeLighter, ms-fontColor-white, ms-fontColor-white--hover"
      }
    ],
    "thumbnails": [
      {
        "type": "image",
        "order": 100,
        "url": "https://raw.githubusercontent.com/pnp/List-Formatting/master/column-samples/hyperlink-click-count/assets/screenshot.gif",
        "alt": "zrzut ekranu"
      }
    ],
    "authors": [
      {
        "gitHubAccount": "tecchan1107",
        "pictureUrl": "https://github.com/tecchan1107.png",
        "name": "Tetsuya Kawahara"
      }
    ],
    "references": [
      {
        "name": "Użyj formatowania kolumn do dostosowania SharePoint",
        "description": "Możesz użyć formatowania kolumn, aby dostosować sposób wyświetlania pól na listach i w bibliotekach SharePoint. W tym celu tworzysz obiekt JSON opisujący elementy wyświetlane wtedy, gdy pole jest uwzględnione w widoku listy, oraz style stosowane do tych elementów. Formatowanie kolumn nie zmienia danych elementu listy ani pliku; zmienia jedynie sposób ich wyświetlania użytkownikom przeglądającym listę.",
        "url": "https://docs.microsoft.com/sharepoint/dev/declarative-customization/column-formatting"
      }
    ]
  }
]
