[
  {
    "name": "pnp-list-formatting-number-gradation",
    "reponame": "number-gradation",
    "source": "pnp",
    "title": "Number Gradation",
    "shortDescription": "Ta próbka pokazuje a gradual background color change between the minimum and maximum values.",
    "url": "https://github.com/pnp/List-Formatting/tree/master/column-samples/number-gradation",
    "longDescription": [
      "Ta próbka pokazuje a gradual background color change between the minimum and maximum values."
    ],
    "creationDateTime": "2022-04-08T00:00:00.000Z",
    "updateDateTime": "2022-04-08T00:00:00.000Z",
    "products": [
      "SharePoint",
      "Microsoft Lists"
    ],
    "metadata": [
      {
        "key": "LIST-SAMPLE-TYPE",
        "value": "Column"
      },
      {
        "key": "SHAREPOINT-COMPATIBILITY",
        "value": "SharePoint Online"
      },
      {
        "key": "SAMPLE-CATEGORIES",
        "value": ""
      },
      {
        "key": "LIST-COLUMN-TYPE",
        "value": "Number"
      },
      {
        "key": "FORMATTING-TOKENS",
        "value": ""
      },
      {
        "key": "FORMATTING-OPERATORS",
        "value": "abs"
      },
      {
        "key": "FORMATTING-ACTIONS",
        "value": ""
      },
      {
        "key": "FORMATTING-FEATURES",
        "value": ""
      },
      {
        "key": "CLASSES",
        "value": ""
      }
    ],
    "thumbnails": [
      {
        "type": "image",
        "order": 100,
        "url": "https://raw.githubusercontent.com/pnp/List-Formatting/master/column-samples/number-gradation/assets/screenshot.png",
        "alt": "zrzut ekranu"
      }
    ],
    "authors": [
      {
        "gitHubAccount": "tecchan1107",
        "pictureUrl": "https://github.com/tecchan1107.png",
        "name": "Tetsuya Kawahara"
      }
    ],
    "references": [
      {
        "name": "Użyj formatowania kolumn do dostosowania SharePoint",
        "description": "Możesz użyć formatowania kolumn, aby dostosować sposób wyświetlania pól na listach i w bibliotekach SharePoint. W tym celu tworzysz obiekt JSON opisujący elementy wyświetlane wtedy, gdy pole jest uwzględnione w widoku listy, oraz style stosowane do tych elementów. Formatowanie kolumn nie zmienia danych elementu listy ani pliku; zmienia jedynie sposób ich wyświetlania użytkownikom przeglądającym listę.",
        "url": "https://docs.microsoft.com/sharepoint/dev/declarative-customization/column-formatting"
      }
    ]
  }
]
